ghttp/__init__.py
ghttp/errors.py
ghttp/middleware.py
ghttp/request.py
ghttp/response.py
ghttp/router.py
ghttp/server.py
ghttp-0.0.1.dist-info/LICENSE
ghttp-0.0.1.dist-info/METADATA
ghttp-0.0.1.dist-info/WHEEL
ghttp-0.0.1.dist-info/top_level.txt
ghttp-0.0.1.dist-info/RECORD
